handjoints_osc/__init__.py
handjoints_osc/__main__.py
handjoints_osc-0.0.8.dist-info/METADATA
handjoints_osc-0.0.8.dist-info/WHEEL
handjoints_osc-0.0.8.dist-info/entry_points.txt
handjoints_osc-0.0.8.dist-info/licenses/LICENSE
handjoints_osc-0.0.8.dist-info/RECORD
