Metadata-Version: 2.4
Name: handjoints-osc
Version: 0.0.8
Summary: real-time hands tracker, sends joints coords over OSC
Project-URL: Homepage, https://codeberg.org/elgiano/handjoints-osc
Project-URL: Issues, https://codeberg.org/elgiano/handjoints-osc/issues
Author-email: Gianluca Elia <dev@gianlucaelia.eu>
License-Expression: Unlicense
License-File: LICENSE
Requires-Python: <3.13,>=3.8
Requires-Dist: appdirs
Requires-Dist: mediapipe
Requires-Dist: python-osc
Requires-Dist: requests
Requires-Dist: tqdm
